[
  {
    "shortcode": "CxuZ3fTtgAa",
    "url": "https://www.instagram.com/reel/CxuZ3fTtgAa/",
    "caption": "કોઈ વિકાસ કે ડેવલોપમેન્ટ સાથે વધો નથી .... પણ એટલું નક્કી જરૂર કરવું પડશે કે કેટલું અને ક્યાં વિકાસ ની વ્યાખ્યા વર્તમાન વેચી ને ભવિષ્ય ખરીદવું કેટલું યોગ્ય ....... કચ્છ*ના લોકોએ પણ આ મુદ્દા પર *એકજૂથ* થઈને વિકાસના કામોને સામે સવાલ કરવો જોઈએ , આ વિસ્તારને *કુદરતી* જ રહેવા દેવા માટે આ જરૂરી છે આશા છે આપના શબ્દો અમારી શક્તિ બનશે , લાઈક કરો અને સેર કરો અને આપના શબ્દો માં અમારી શકતી બનો.* https:\\/\\/appopener.com\\/yt\\/8ewafp92k @followers @pmjadejaofficial @vinodchavdabjp @aniruddhdavebjp @mulubhai_bera @incredibleindia",
    "ai_comments_generated": true
  },
  {
    "shortcode": "Cy8U1GiyPbQ",
    "url": "https://www.instagram.com/reel/Cy8U1GiyPbQ/",
    "caption": "\" सबको सन्मति दे भगवान \" परिंदों की करुणामय प्रार्थना #SaveCharidhand #ConserveCharidhand #your_best_birds #kings_birds #birdslife #blackaquamagic #nuts_about_birds #birdfreaks #best_birds_of_ig #bns_birds #birdsofinstagram #nikonindiaofficial #rannofkutch #nikonindia #NPSMember #NikonZ9 #nikonprofessionalservices #ashokchaudhary #ashokchaudharywildlifephotography @narendramodi @gujarat_forest_guard_ @cmogujarat @followers",
    "ai_comments_generated": true
  },
  {
    "shortcode": "C9zz49jyJeh",
    "url": "https://www.instagram.com/reel/C9zz49jyJeh/",
    "caption": "Nikon Nikkor Z 600F\\/4 TC VR S in The Field Review #nikon #nikon600f4 #ashokchaudharyphotography #ashokchaudharywildlifephotography #nikonindiaofficial #wildlifephotographer #wildlifeonearth #viralreels @followers @vinodchavdabjp @aniruddhdavebjp pmjadejaofficial @incredibleindia @gujarattourism @nikonindiaofficial @nikonasia",
    "ai_comments_generated": true
  },
  {
    "shortcode": "DZ5cm1MDy3I",
    "url": "https://www.instagram.com/reel/DZ5cm1MDy3I/",
    "caption": "क़ुदरत ने जो कुछ भी बनाया है, वह लय, संतुलन और प्रेम के साथ बनाया है। चाहे रण हो, समुद्र हो, वर्षावन हो या पहाड़ — हर एक अपनी जगह पर अनूठा, सुंदर और अद्भुत है। इंसान ने जो भी सीखा, क़ुदरत से ही सीखा। रंगों की भाषा, कविता की अभिव्यक्ति, कला का सृजन, जीवन का संगीत — सब उसी की देन हैं। लेकिन न जाने कब इंसान ने सीखने वाले से स्वयं क़ुदरत बनने का सपना देख लिया। विकास के नाम पर हमने बहुत कुछ बनाया, पर उसी के साथ हवा को दूषित किया, नदियों को प्रदूषित किया, जंगलों को उजाड़ा और पहाड़ों की आत्मा तक को खोखला कर दिया। कहीं न कहीं विकास की हमारी परिभाषा रास्ता भटक गई है। क्योंकि सच्चा विकास वह नहीं जो केवल कंक्रीट खड़ा करे, बल्कि वह है जो जीवन को बचाए। जब मैं किरो और छारिदंड की बात करता हूँ, तो कई लोग पूछते हैं — “रेगिस्तान में ऐसा क्या है, जिसके लिए तुम इतना परेशान होते हो?” तब मन मुस्कुरा कर कहता है — कितनी कम समझ है हमारी। कच्छ का रण कोई बंजर ज़मीन नहीं, बल्कि जीवंत ब्रह्मांड है। यहाँ की रेत का हर कण जीवन की कहानी कहता है। किरो के आगन में दुनिया की कई दुर्लभ और विलक्षण प्रजातियाँ अपना घर बनाती हैं। भारतीय लोमड़ी, जंगल कैट, गोल्डन जैकल जैसे स्तनधारी और आकाश के गौरव कहे जाने वाले साकर फ़ाल्कन, लगर फ़ाल्कन, किंग वल्चर, स्टेपी ईगल और लॉन्ग-लेग्ड बज़र्ड जैसे दुर्लभ रैप्टर इस भूमि की पहचान हैं। यह सिर्फ़ पक्षियों और जानवरों का घर नहीं है, यह उस संतुलन का प्रतीक है जिसे क़ुदरत ने लाखों वर्षों में रचा है। मेरी विनती केवल इतनी है — किरो और छारिदंड को किसी परियोजना, किसी नक्शे या किसी आँकड़े की नज़र से मत देखिए। इसे एक जीवित आत्मा की तरह देखिए। अगर हम आज इस संतुलन को नहीं बचा पाए, तो आने वाली पीढ़ियाँ हमसे पूछेंगी कि जब क़ुदरत मदद के लिए पुकार रही थी, तब हम खामोश क्यों थे। क्योंकि कुछ जगहें विकास के लिए नहीं, बल्कि संरक्षण के लिए बनाई जाती हैं। और किरो, कच्छ के रण की ऐसी ही एक पवित्र अमानत है। #SaveKiro #SaveChharidhand #LandOfRaptors #kutchbiodiversity #natureneedsprotectiomeat",
    "ai_comments_generated": true
  },
  {
    "shortcode": "DZ47d8YvM3D",
    "url": "https://www.instagram.com/reel/DZ47d8YvM3D/",
    "caption": "#ashokchaudharywildlifephotography #ashokchaudhary",
    "ai_comments_generated": true
  },
  {
    "shortcode": "DZ4FR5dPEO8",
    "url": "https://www.instagram.com/reel/DZ4FR5dPEO8/",
    "caption": "#ashokchaudharywildlifephotography #kutch #wildlifephotography #savekirohill #savecharidhand",
    "ai_comments_generated": true
  },
  {
    "shortcode": "DZzJ4IVD9SC",
    "url": "https://www.instagram.com/reel/DZzJ4IVD9SC/",
    "caption": "Short-eared Owl (Asio flammeus) રવાઈડો ઘુવડ , ટૂંકા કાનવાળું ઘુવડ— किरो की सर्दियों का मौन मेहमान कई लोगों को किरो और उसके आसपास का रेगिस्तान एक सूनी, बंजर और निर्जन भूमि दिखाई देता है। लेकिन जो आँखें प्रकृति को पढ़ना जानती हैं, उन्हें कच्छ की इस धरती का हर कण जीवन से भरा दिखाई देता है। यहीं, हवा की सरगोशियों और घास के समुद्र के बीच, अनेक स्थानीय पक्षी अपना घर बनाते हैं। और हर सर्दी, हजारों किलोमीटर दूर से एक विशेष मेहमान इस धरती पर उतरता है — Short-eared Owl। दिन के उजाले में भी उड़ान भरने वाला यह खूबसूरत उल्लू कच्छ के घासस्थलों और रेगिस्तानी विस्तारों को अपना अस्थायी आशियाना बनाता है। इसकी मौजूदगी हमें याद दिलाती है कि जिसे हम वीरान समझते हैं, वह किसी और के लिए जीवन, सुरक्षा और आश्रय का संसार है। आज जब विकास और संरक्षण के बीच संतुलन की बात हो रही है, तब यह ज़रूरी है कि हम इन मौन मेहमानों की आवाज़ भी सुनें। क्योंकि अगर घास के ये मैदान, ये खुले विस्तार और ये प्राकृतिक आवास खो गए, तो केवल एक पक्षी नहीं, बल्कि सदियों पुराना एक प्राकृतिक रिश्ता भी खो जाएगा। किरो सिर्फ एक भूभाग नहीं है, यह प्रवासी परिंदों की उम्मीद, विश्राम और जीवन की कहानी है। #SaveKiro #KutchWildlife #ShortEaredOwl #BirdConservation #NaturePhotography 🦉🌾🌍",
    "ai_comments_generated": true
  },
  {
    "shortcode": "DZuoV13j200",
    "url": "https://www.instagram.com/reel/DZuoV13j200/",
    "caption": "🐾 जंगल कैट (Felis chaus) – घास के मैदानों का मौन शिकारी 🐾 कच्छ की घासभूमियों, आर्द्रभूमियों और झाड़ियों के बीच एक ऐसा शिकारी भी रहता है जो अक्सर हमारी नजरों से ओझल रहता है। जंगल कैट (Felis chaus) अपनी तीव्र इंद्रियों, फुर्ती और अद्भुत शिकार कौशल के लिए जानी जाती है। घरेलू बिल्ली से बड़ी दिखने वाली यह खूबसूरत जंगली बिल्ली पारिस्थितिकी तंत्र का महत्वपूर्ण हिस्सा है। यह चूहों और अन्य छोटे जीवों की संख्या को नियंत्रित कर प्रकृति के संतुलन को बनाए रखने में मदद करती है। जंगल की खामोशी में इसकी एक झलक मिलना किसी वन्यजीव प्रेमी के लिए किसी सौभाग्य से कम नहीं। आइए, इस रहस्यमयी शिकारी और इसके प्राकृतिक आवास के संरक्षण के लिए जागरूक बनें। 📸: Ashok M. Chaudhary Description A rare glimpse of the elusive Jungle Cat (Felis chaus), one of India’s most fascinating wild felines. Found in grasslands, wetlands, and scrub habitats, this agile predator plays a vital role in maintaining ecological balance. Protecting its habitat means protecting an entire ecosystem. #JungleCat #FelisChaus #WildlifePhotography #KutchWildlife #NatureConservation",
    "ai_comments_generated": true
  },
  {
    "shortcode": "DZmyk_tPyhO",
    "url": "https://www.instagram.com/reel/DZmyk_tPyhO/",
    "caption": "#ashokchaudharywildlifephotography #kutch #nikonindiaofficial #viralreels #wildlifephotography",
    "ai_comments_generated": true
  },
  {
    "shortcode": "DZmB95ADzjt",
    "url": "https://www.instagram.com/reel/DZmB95ADzjt/",
    "caption": "हम विकास के विरोधी नहीं हैं। पर विकास कहाँ हो, कितना हो, और किस कीमत पर हो — यह सवाल पूछना भी उतना ही ज़रूरी है। कच्छ की इस धरती पर एक ऐसा स्वर्ग है, जिसे हम “किरो” के नाम से जानते हैं। एक विलुप्त ज्वालामुखी, जिसके आसपास की मिट्टी में करोड़ों वर्षों का इतिहास सांस लेता है। मिडिल जुरासिक काल के जीवाश्म, दुर्लभ वनस्पतियाँ, पशुधन के चरागाह, और सर्दियों में दूर देशों से आने वाले हजारों कॉमन क्रेन — सबने इस भूमि को अपना घर चुना है। मेरे लिए किरो सिर्फ़ एक जगह नहीं है। यह एक एहसास है, एक इबादत है, एक ऐसी ख़ामोशी है जहाँ प्रकृति स्वयं अपनी प्रार्थना करती है। छारी ढंढ़ और किरो मेरे दिल के बेहद क़रीब हैं, और मैं जानता हूँ कि मैं अकेला नहीं हूँ। अनगिनत लोगों के लिए यह स्थान प्रेरणा, शांति और आत्मिक जुड़ाव का स्रोत रहा है। एक कलाकार होने के नाते मैं अपने मन को कल्पना करने से रोक नहीं पाया। मैंने AI की सहायता से एक तस्वीर बनाई है — एक ऐसी तस्वीर, जो शायद आने वाले समय की सच्चाई बन सकती है। और यह कल्पना मुझे भीतर तक बेचैन कर देती है। जहाँ आज परिंदे अपने पंखों को विश्राम देते हैं, जहाँ पशुधन जीवन पाता है, जहाँ हवा में दुआओं जैसी शांति घुली रहती है, वहीं कल शायद मशीनों का शोर होगा। प्रकृति कभी अपने लिए नहीं बोलती। न पक्षी अदालत जाते हैं, न जीवाश्म ज्ञापन लिखते हैं, न घास के मैदान विरोध प्रदर्शन करते हैं। उनकी आवाज़ हमें बनना पड़ता है। मैं फिर कहूँगा — हम विकास के विरोधी नहीं हैं। लेकिन ऐसा विकास, जो अपनी जड़ों को ही काट दे, वह अंततः विनाश का दूसरा नाम बन जाता है। किरो केवल कच्छ की धरोहर नहीं है, यह आने वाली पीढ़ियों की अमानत है। यह स्थान एक जियो-पार्क, एक जीवित प्राकृतिक विरासत और विश्वस्तरीय संरक्षण क्षेत्र बनने की क्षमता रखता है। इसे उसके मूल स्वरूप में छोड़ देना ही शायद इस धरती के प्रति हमारी सबसे बड़ी श्रद्धांजलि होगी। आप सभी से विनम्र निवेदन है — अपने विचार लिखिए, इस पोस्ट और रील को आगे बढ़ाइए। ताकि निर्णय लेने वालों तक यह एहसास पहुँचे कि कुछ जगहें केवल ज़मीन नहीं होतीं, वे लोगों की स्मृतियाँ, आस्था और आत्मा होती हैं। कहीं ऐसा न हो कि कल हम अपने बच्चों को तस्वीरें दिखाकर कहें — “यहाँ कभी किरो हुआ करता था…” और वे पूछें — “फिर आपने उसे बचाया क्यों नहीं?” 🕊️💔🌿",
    "ai_comments_generated": true
  },
  {
    "shortcode": "DZjh684PWv4",
    "url": "https://www.instagram.com/reel/DZjh684PWv4/",
    "caption": "कच्छ और कुच्छियत की बात है अब क्या अपनी मिट्टी से इतना ही लगाव है , क्या इस मिट्टी की महेक में अपना इतिहास नहीं अपने बड़े अपने बुजर्गो की महेनत का पसीना नहीं , सोचो",
    "ai_comments_generated": true
  },
  {
    "shortcode": "DZhQiBvqCka",
    "url": "https://www.instagram.com/reel/DZhQiBvqCka/",
    "caption": "This reel highlights the story of Chhari Dhandh , informed to us by activist and wildlife photographer Mr @ashok__chaudhary___ Gujarat’s Ramsar wetland, and the concerns surrounding a proposed solar project near its boundary. More than 50,000 migratory birds depend on these wetlands every winter, reminding us that conservation cannot be an afterthought. The real solution lies in ensuring that every department performs its duties with a conservation-first approach, protecting wetlands, wildlife, and ecological balance while pursuing development. Wetlands need protection beyond recognition. [Chhari Dhandh, Ramsar Site, Gujarat Wetlands, Wetland Conservation, Migratory Birds, Bird Conservation, Wildlife Protection, Environmental Conservation, Sustainable Development, Solar Project, Biodiversity, Nature Conservation, Ramsar Convention, Ashok Chaudhary]",
    "ai_comments_generated": true
  },
  {
    "shortcode": "DZeQjnMvYsJ",
    "url": "https://www.instagram.com/reel/DZeQjnMvYsJ/",
    "caption": "#ashokchaudharywildlifephotography #kutch #nikonindiaofficial #savekiro #savekirohill",
    "ai_comments_generated": true
  },
  {
    "shortcode": "DZcWwCBPa2i",
    "url": "https://www.instagram.com/reel/DZcWwCBPa2i/",
    "caption": "#savekiro #savekirohill #savecharidhand #ashokchaudharywildlifephotography",
    "ai_comments_generated": true
  },
  {
    "shortcode": "DYGYOLaIRfP",
    "url": "https://www.instagram.com/reel/DYGYOLaIRfP/",
    "caption": "ये एक कोशिश है वो पाप करने से रोकनेकी जिससे लाखो परिंदे अपना घर खो देगे, सारे फ़ुटेज उसी जगह की है, पशु पक्षी के लिए कायदे की भाषा समझना मुमकिन नहीं, अपने आए उससे भी पहले से उस जगह ये परिंदे वही रहते आए है ।#ashokchaudharywildlifephotography #kutch #savekirohill #viralreels #savcharidhandh",
    "ai_comments_generated": true
  },
  {
    "shortcode": "DYYP_lCvzlX",
    "url": "https://www.instagram.com/reel/DYYP_lCvzlX/",
    "caption": "कच्छ के छारिदंड की खामोश रूह में एक नाम बार-बार धड़कता है — किरो…यह सिर्फ़ पत्थरों का ढेर नहीं, यह समय का साधक है, दिशाओं का रखवाला, और भटके कदमों का रहबर#savekiro #savekirohill #savecharidhand #ashokchaudharywildlifephotography #viralreels",
    "ai_comments_generated": true
  },
  {
    "shortcode": "DZPwQDDRUu4",
    "url": "https://www.instagram.com/reel/DZPwQDDRUu4/",
    "caption": "विकास तभी सार्थक है, जब प्रकृति भी मुस्कुराए, सिर्फ इंसान नहीं, हर जीव सुरक्षित रह पाए। तरक्की वही जो आने वाली पीढ़ियों को जीवन दे, न कि ऐसा कल, जो आज की साँसें ही छीन ले। #SaveNature #SustainableDevelopment #EnvironmentProtection #WildlifeConservation #GreenFuture NatureMatters EarthFirst ClimateAction ProtectOurPlanet EcoFriendly ",
    "ai_comments_generated": true
  },
  {
    "shortcode": "DZC__Xbkn-H",
    "url": "https://www.instagram.com/reel/DZC__Xbkn-H/",
    "caption": "जवाई और कच्छ का तेंदुआ — एक सूफ़ियाना रिश्ता पत्थरों की खामोशी में भी एक ज़िक्र होता है, और जंगल की तन्हाई में भी एक आवाज़ गूंजती है। जवाई की इन विशाल चट्टानों के बीच बैठा यह भारतीय तेंदुआ मानो उसी अनकहे ज़िक्र का पहरेदार हो। पिछली गर्मियों में आबू-जवाई की यात्रा केवल वन्यजीवन देखने की यात्रा नहीं थी, बल्कि प्रकृति के उस रहस्य को महसूस करने का अवसर थी जहाँ इंसान, पशु, पर्वत और समय एक ही धागे में बंधे दिखाई देते हैं। कच्छ और जवाई के तेंदुओं के बीच एक अद्भुत तालमेल महसूस हुआ। धरती अलग है, पर स्वभाव एक जैसा। दोनों ने कठोर परिस्थितियों में जीना सीखा है, दोनों ने इंसानों के साथ सह-अस्तित्व का मार्ग चुना है, और दोनों अपनी मौन उपस्थिति से यह सिखाते हैं कि शक्ति का सबसे सुंदर रूप विनम्रता में छिपा होता है। सूफ़ी संत कहते हैं कि सृष्टि का हर जीव अपने रचयिता का एक अक्षर है। जब तेंदुआ इन चट्टानों के बीच निस्संग बैठा दिखाई देता है, तब वह केवल एक शिकारी नहीं रहता, बल्कि प्रकृति की उस आध्यात्मिक पुस्तक का एक पन्ना बन जाता है जिसे पढ़ने के लिए आँखों से अधिक दिल की आवश्यकता होती है। जवाई की चट्टानें और भारतीय तेंदुआ एक-दूसरे के पूरक हैं। जैसे साधक और उसकी तपस्थली, जैसे रूह और उसका सुकून। चट्टानें उसे आश्रय देती हैं और तेंदुआ उन चट्टानों को अर्थ देता है। उस क्षण को कैमरे में कैद करते हुए ऐसा लगा मानो प्रकृति कह रही हो— “जो स्वयं को प्रकृति में खो देता है, वही अपने भीतर के सत्य को पा लेता है।” जवाई के पत्थरों में बैठा तेंदुआ केवल वन्यजीव नहीं, बल्कि ख़ुदा की बनाई उस ख़ामोश कविता का एक शेर है, जिसे सुनने के लिए दिल का जागना ज़रूरी है।  आबू-जवाई, ग्रीष्मकाल 2025 — अशोक एम. चौधरी | स्पंदन पिक्सल",
    "ai_comments_generated": true
  },
  {
    "shortcode": "DZATijhIb7e",
    "url": "https://www.instagram.com/reel/DZATijhIb7e/",
    "caption": "#ashokchaudharywildlifephotography #kutch #nikonindiaofficial #viralreels #wildlifephotographer",
    "ai_comments_generated": true
  },
  {
    "shortcode": "DYjzA0BvrUt",
    "url": "https://www.instagram.com/reel/DYjzA0BvrUt/",
    "caption": "કોઈ વિકાસ કે ડેવલોપમેન્ટ સાથે વધો નથી .... પણ એટલું નક્કી જરૂર કરવું પડશે કે કેટલું અને ક્યાં વિકાસ ની વ્યાખ્યા વર્તમાન વેચી ને ભવિષ્ય ખરીદવું કેટલું યોગ્ય ....... કચ્છ*ના લોકોએ પણ આ મુદ્દા પર *એકજૂથ* થઈને વિકાસના કામોને સામે સવાલ કરવો જોઈએ , આ વિસ્તારને *કુદરતી* જ રહેવા દેવા માટે આ જરૂરી છે આશા છે આપના શબ્દો અમારી શક્તિ બનશે , લાઈક કરો અને સેર કરો અને આપના શબ્દો માં અમારી શકતી બનો.* https:\\/\\/appopener.com\\/yt\\/8ewafp92k @followers @pmjadejaofficial @vinodchavdabjp @aniruddhdavebjp @mulubhai_bera @incredibleindia",
    "ai_comments_generated": true
  },
  {
    "shortcode": "DYwt8iCPBHD",
    "url": "https://www.instagram.com/reel/DYwt8iCPBHD/",
    "caption": "કોઈ વિકાસ કે ડેવલોપમેન્ટ સાથે વધો નથી .... પણ એટલું નક્કી જરૂર કરવું પડશે કે કેટલું અને ક્યાં વિકાસ ની વ્યાખ્યા વર્તમાન વેચી ને ભવિષ્ય ખરીદવું કેટલું યોગ્ય ....... કચ્છ*ના લોકોએ પણ આ મુદ્દા પર *એકજૂથ* થઈને વિકાસના કામોને સામે સવાલ કરવો જોઈએ , આ વિસ્તારને *કુદરતી* જ રહેવા દેવા માટે આ જરૂરી છે આશા છે આપના શબ્દો અમારી શક્તિ બનશે , લાઈક કરો અને સેર કરો અને આપના શબ્દો માં અમારી શકતી બનો.* https:\\/\\/appopener.com\\/yt\\/8ewafp92k @followers @pmjadejaofficial @vinodchavdabjp @aniruddhdavebjp @mulubhai_bera @incredibleindia",
    "ai_comments_generated": true
  },
  {
    "shortcode": "DY5w1-JILux",
    "url": "https://www.instagram.com/reel/DY5w1-JILux/",
    "caption": "Dev Prakash Bamanavat IRS Additional Commissioner GST Kutch #spandanpixel #viralreels #wildlifephotographer",
    "ai_comments_generated": true
  },
  {
    "shortcode": "DY6cp6cIbWS",
    "url": "https://www.instagram.com/reel/DY6cp6cIbWS/",
    "caption": "​\"વિકાસની ગાડી એટલી ફાસ્ટ દોડી રહી છે કે રસ્તામાં આવતા અબોલ જીવોનો કચડાવવાનો અવાજ કોઈને સંભળાતો જ નથી #savekiro #savecharidhand #",
    "ai_comments_generated": true
  },
  {
    "shortcode": "DY5vuDViE_L",
    "url": "https://www.instagram.com/reel/DY5vuDViE_L/",
    "caption": "स्पंदन पिक्सल आर्ट गैलेरी के आंगन में आज की यह मुलाक़ात सच में बेहद विशेष, आत्मीय और प्रेरणादायी रही। आज गैलेरी में पधारे श्री Prakash Bamanavat साथ में उनके मित्र श्री. Gauri Shankar Meena Superintendent GST एवं श्री.Chhoti Lal Meena, TA, GST देव प्रकाश जी से लंबे समय से बातचीत और मिलने का सिलसिला चल रहा था, और आज आखिरकार वह सुंदर पल आ ही गया जब उन्होंने अपने व्यस्त समय में से कुछ अनमोल क्षण निकालकर स्पंदन पिक्सल आने का स्नेह दिया। पहली मुलाक़ात में ही उनका व्यक्तित्व मन को छू लेने वाला लगा — बेहद सरल, विनम्र, संवेदनशील और आत्मीय। प्रशासनिक ज़िम्मेदारियों के इतने महत्वपूर्ण पद पर होने के बावजूद उनके भीतर का कलाकार आज भी उतनी ही खूबसूरती से जीवित है। देव प्रकाश जी केवल एक कुशल अधिकारी ही नहीं, बल्कि कला को महसूस करने वाले, संवेदनाओं को समझने वाले और प्रकृति व सृजन से गहरा जुड़ाव रखने वाले एक उम्दा इंसान हैं। उनकी बातचीत में सहजता थी, विचारों में गहराई थी और कला के प्रति एक सच्चा सम्मान महसूस होता था। ऐसे व्यक्तित्व बहुत कम मिलते हैं जो अपने पद से नहीं, बल्कि अपने स्वभाव और व्यवहार से दिल जीत लेते हैं। आज की यह मुलाक़ात केवल एक औपचारिक भेंट नहीं रही, बल्कि कला, संवेदनाओं और आत्मीय संवाद से भरा एक यादगार अनुभव बन गई। स्पंदन पिक्सल परिवार की ओर से देव प्रकाश जी, शंकर मीणा जी और लाल मीणा जी का हृदय से आभार एवं स्नेहपूर्ण स्वागत। ईश्वर से प्रार्थना है कि आप सभी सदैव स्वस्थ, प्रसन्न और प्रेरणादायी बने रहें।",
    "ai_comments_generated": true
  },
  {
    "shortcode": "DYvtzigCAx9",
    "url": "https://www.instagram.com/reel/DYvtzigCAx9/",
    "caption": "स्पंदन पिक्सल आर्ट गैलेरी में आज का दिन सिर्फ़ एक मुलाक़ात नहीं था… यह आत्माओं का संगम था, संवेदनाओं का उत्सव था, और उस दिव्य ऊर्जा का स्पर्श था जिसे शब्दों में बाँध पाना आसान नहीं। फ़ोटोग्राफ़ी केवल कैमरे से दृश्य कैद करने की कला नहीं, यह एक आध्यात्मिक यात्रा है… जहाँ रास्तों में प्रकृति मिलती है, पक्षियों का संगीत मिलता है, और कभी-कभी ऐसे अद्भुत इंसान मिल जाते हैं जिनकी आत्मा की रोशनी देर तक भीतर जगमगाती रहती है। काफी लंबे समय से आदरणीय Chaitanya Shroff से संवाद और आत्मीय बातचीत का सिलसिला चल रहा था, और आज वह प्रतीक्षित, अलौकिक और बेहद सुंदर क्षण आखिरकार स्पंदन पिक्सल की चौखट तक आ ही पहुँचा। आज वे अपने पूरे परिवार के साथ पधारे — ससुरजी, सासुमाँ, Dr. Parthiv Asher Priya Asher और नन्ही बच्चा पार्टी के Keya & Ayaan Shayna Asher,Maisha Asher,Kabir Dayal साथ पर उनके स्नेह, अपनापन और मुस्कानों ने आज गैलेरी की हर दीवार को जीवंत कर दिया। श्री चैतन्य भाई का व्यक्तित्व ऐसा है जिसमें विनम्रता किसी शांत नदी की तरह बहती है। ऊँचा पद, विशाल अनुभव और इतनी उपलब्धियों के बावजूद उनकी सहजता मन को तुरंत छू जाती है। और फिर श्री काका… उनकी आँखों में जो अपनापन और आत्मीयता थी, वह किसी सूफी दरवेश की दुआ जैसी लगी। सच कहूँ तो, ऐसे परिवारों से मिलकर महसूस होता है कि महानता शोर में नहीं, सरलता में बसती है। इतनी सहजता, इतनी निर्मलता और इतना प्रेम… कोई भी हृदय इससे अछूता कैसे रह सकता है? आज स्पंदन पिक्सल सिर्फ़ एक आर्ट गैलेरी नहीं रहा, आज यह प्रेम, संस्कार, संवेदना और आत्मिक ऊर्जा का एक जीवंत आश्रम बन गया। इस अलौकिक मुलाक़ात के लिए हृदय से आभार। कुछ पल तस्वीरों में कैद होते हैं… और कुछ पल सीधे आत्मा में उतर जाते हैं। आज का दिन उन्हीं दुर्लभ पलों में से एक रहा।",
    "ai_comments_generated": true
  },
  {
    "shortcode": "DYmCbvKoPwP",
    "url": "https://www.instagram.com/reel/DYmCbvKoPwP/",
    "caption": "કોઈ વિકાસ કે ડેવલોપમેન્ટ સાથે વધો નથી .... પણ એટલું નક્કી જરૂર કરવું પડશે કે કેટલું અને ક્યાં વિકાસ ની વ્યાખ્યા વર્તમાન વેચી ને ભવિષ્ય ખરીદવું કેટલું યોગ્ય ....... કચ્છ*ના લોકોએ પણ આ મુદ્દા પર *એકજૂથ* થઈને વિકાસના કામોને સામે સવાલ કરવો જોઈએ , આ વિસ્તારને *કુદરતી* જ રહેવા દેવા માટે આ જરૂરી છે આશા છે આપના શબ્દો અમારી શક્તિ બનશે , લાઈક કરો અને સેર કરો અને આપના શબ્દો માં અમારી શકતી બનો.* https:\\/\\/appopener.com\\/yt\\/8ewafp92k @followers @pmjadejaofficial @vinodchavdabjp @aniruddhdavebjp @mulubhai_bera @incredibleindia",
    "ai_comments_generated": true
  }
]